{"lastUsed":1612158035457,"path":"D:\/A_TeachingMaterial\/3.HighJava","projectCount":10,"recentFiles":[{"path":"\/jdbcTest\/src\/kr\/or\/ddit\/basic","parentWorkspace":"D:\/A_TeachingMaterial\/3.HighJava","name":"JdbcTest20.java","lastModified":1611731346035,"locationURI":"file:\/D:\/A_TeachingMaterial\/3.HighJava\/jdbcTest\/src\/kr\/or\/ddit\/basic\/JdbcTest20.java"},{"path":"\/consoleBoard\/src\/kr\/or\/ddit\/mvc\/util","parentWorkspace":"D:\/A_TeachingMaterial\/3.HighJava","name":"test.java","lastModified":1612158039538,"locationURI":"file:\/D:\/A_TeachingMaterial\/3.HighJava\/consoleBoard\/src\/kr\/or\/ddit\/mvc\/util\/test.java"},{"path":"\/consoleBoard\/src\/consoleBoard_service","parentWorkspace":"D:\/A_TeachingMaterial\/3.HighJava","name":"consoleBoard_ServiceImpl.java","lastModified":1612158039538,"locationURI":"file:\/D:\/A_TeachingMaterial\/3.HighJava\/consoleBoard\/src\/consoleBoard_service\/consoleBoard_ServiceImpl.java"},{"path":"\/jdbcTest\/src\/kr\/or\/ddit\/basic","parentWorkspace":"D:\/A_TeachingMaterial\/3.HighJava","name":"JDBCTest03.java","lastModified":1611560073047,"locationURI":"file:\/D:\/A_TeachingMaterial\/3.HighJava\/jdbcTest\/src\/kr\/or\/ddit\/basic\/JDBCTest03.java"},{"path":"\/jdbcTest\/src\/kr\/or\/ddit\/basic","parentWorkspace":"D:\/A_TeachingMaterial\/3.HighJava","name":"JdbcTest06.java","lastModified":1611647150071,"locationURI":"file:\/D:\/A_TeachingMaterial\/3.HighJava\/jdbcTest\/src\/kr\/or\/ddit\/basic\/JdbcTest06.java"},{"path":"\/jdbcTest\/src\/kr\/or\/ddit\/basic","parentWorkspace":"D:\/A_TeachingMaterial\/3.HighJava","name":"JdbcTest05.java","lastModified":1611731346035,"locationURI":"file:\/D:\/A_TeachingMaterial\/3.HighJava\/jdbcTest\/src\/kr\/or\/ddit\/basic\/JdbcTest05.java"},{"path":"\/jdbcTest\/src\/kr\/or\/ddit\/util","parentWorkspace":"D:\/A_TeachingMaterial\/3.HighJava","name":"PropertiesTest.java","lastModified":1611732133060,"locationURI":"file:\/D:\/A_TeachingMaterial\/3.HighJava\/jdbcTest\/src\/kr\/or\/ddit\/util\/PropertiesTest.java"},{"path":"\/jdbcTest\/src\/kr\/or\/ddit\/util","parentWorkspace":"D:\/A_TeachingMaterial\/3.HighJava","name":"DBUtil3.java","lastModified":1611734613682,"locationURI":"file:\/D:\/A_TeachingMaterial\/3.HighJava\/jdbcTest\/src\/kr\/or\/ddit\/util\/DBUtil3.java"},{"path":"\/jdbcTest\/src\/kr\/or\/ddit\/mvc\/service","parentWorkspace":"D:\/A_TeachingMaterial\/3.HighJava","name":"IMemberService.java","lastModified":1611900494803,"locationURI":"file:\/D:\/A_TeachingMaterial\/3.HighJava\/jdbcTest\/src\/kr\/or\/ddit\/mvc\/service\/IMemberService.java"},{"path":"\/jdbcTest\/src\/kr\/or\/ddit\/util","parentWorkspace":"D:\/A_TeachingMaterial\/3.HighJava","name":"DBUtil2.java","lastModified":1611733080466,"locationURI":"file:\/D:\/A_TeachingMaterial\/3.HighJava\/jdbcTest\/src\/kr\/or\/ddit\/util\/DBUtil2.java"},{"path":"\/jdbcTest\/src\/kr\/or\/ddit\/basic","parentWorkspace":"D:\/A_TeachingMaterial\/3.HighJava","name":"JdbcTest04.java","lastModified":1611633164759,"locationURI":"file:\/D:\/A_TeachingMaterial\/3.HighJava\/jdbcTest\/src\/kr\/or\/ddit\/basic\/JdbcTest04.java"},{"path":"\/proGramers\/src\/proGramers","parentWorkspace":"D:\/A_TeachingMaterial\/3.HighJava","name":"이상한문자.java","lastModified":1611554723432,"locationURI":"file:\/D:\/A_TeachingMaterial\/3.HighJava\/proGramers\/src\/proGramers\/이상한문자.java"},{"path":"\/jdbcTest\/src\/kr\/or\/ddit\/basic","parentWorkspace":"D:\/A_TeachingMaterial\/3.HighJava","name":"JdbcTest02.java","lastModified":1611562466707,"locationURI":"file:\/D:\/A_TeachingMaterial\/3.HighJava\/jdbcTest\/src\/kr\/or\/ddit\/basic\/JdbcTest02.java"},{"path":"\/jdbcTest\/src\/kr\/or\/ddit\/basic","parentWorkspace":"D:\/A_TeachingMaterial\/3.HighJava","name":"JdbcTest01.java","lastModified":1611559309808,"locationURI":"file:\/D:\/A_TeachingMaterial\/3.HighJava\/jdbcTest\/src\/kr\/or\/ddit\/basic\/JdbcTest01.java"},{"path":"\/jdbcTest\/src\/kr\/or\/ddit\/mvc\/vo","parentWorkspace":"D:\/A_TeachingMaterial\/3.HighJava","name":"MemberVO.java","lastModified":1611820010557,"locationURI":"file:\/D:\/A_TeachingMaterial\/3.HighJava\/jdbcTest\/src\/kr\/or\/ddit\/mvc\/vo\/MemberVO.java"},{"path":"\/jdbcTest\/src\/kr\/or\/ddit\/basic\/singlton","parentWorkspace":"D:\/A_TeachingMaterial\/3.HighJava","name":"SingletonTest.java","lastModified":1611898898255,"locationURI":"file:\/D:\/A_TeachingMaterial\/3.HighJava\/jdbcTest\/src\/kr\/or\/ddit\/basic\/singlton\/SingletonTest.java"},{"path":"\/jdbcTest\/src\/kr\/or\/ddit\/mvc\/controller","parentWorkspace":"D:\/A_TeachingMaterial\/3.HighJava","name":"MemberController.java","lastModified":1611900755901,"locationURI":"file:\/D:\/A_TeachingMaterial\/3.HighJava\/jdbcTest\/src\/kr\/or\/ddit\/mvc\/controller\/MemberController.java"},{"path":"\/jdbcTest\/src\/kr\/or\/ddit\/util","parentWorkspace":"D:\/A_TeachingMaterial\/3.HighJava","name":"ResouceBundleTest.java","lastModified":1611734246923,"locationURI":"file:\/D:\/A_TeachingMaterial\/3.HighJava\/jdbcTest\/src\/kr\/or\/ddit\/util\/ResouceBundleTest.java"},{"path":"\/jdbcTest\/src\/kr\/or\/ddit\/mvc\/service","parentWorkspace":"D:\/A_TeachingMaterial\/3.HighJava","name":"MemberServiceImpl.java","lastModified":1611900628391,"locationURI":"file:\/D:\/A_TeachingMaterial\/3.HighJava\/jdbcTest\/src\/kr\/or\/ddit\/mvc\/service\/MemberServiceImpl.java"},{"path":"\/jdbcTest\/src\/kr\/or\/ddit\/basic","parentWorkspace":"D:\/A_TeachingMaterial\/3.HighJava","name":"JdbcTest07.java","lastModified":1611808320193,"locationURI":"file:\/D:\/A_TeachingMaterial\/3.HighJava\/jdbcTest\/src\/kr\/or\/ddit\/basic\/JdbcTest07.java"},{"path":"\/consoleBoard\/src\/consoleBoard_VO","parentWorkspace":"D:\/A_TeachingMaterial\/3.HighJava","name":"MemberVO.java","lastModified":1612158039538,"locationURI":"file:\/D:\/A_TeachingMaterial\/3.HighJava\/consoleBoard\/src\/consoleBoard_VO\/MemberVO.java"},{"path":"\/jdbcTest\/src\/kr\/or\/ddit\/mvc\/dao","parentWorkspace":"D:\/A_TeachingMaterial\/3.HighJava","name":"memberDaoImpl.java","lastModified":1611900063585,"locationURI":"file:\/D:\/A_TeachingMaterial\/3.HighJava\/jdbcTest\/src\/kr\/or\/ddit\/mvc\/dao\/memberDaoImpl.java"},{"path":"\/jdbcTest\/src\/kr\/or\/ddit\/util","parentWorkspace":"D:\/A_TeachingMaterial\/3.HighJava","name":"DBUtil.java","lastModified":1611647078460,"locationURI":"file:\/D:\/A_TeachingMaterial\/3.HighJava\/jdbcTest\/src\/kr\/or\/ddit\/util\/DBUtil.java"},{"path":"\/jdbcTest\/src\/kr\/or\/ddit\/mvc\/dao","parentWorkspace":"D:\/A_TeachingMaterial\/3.HighJava","name":"IMemberDao.java","lastModified":1611899825082,"locationURI":"file:\/D:\/A_TeachingMaterial\/3.HighJava\/jdbcTest\/src\/kr\/or\/ddit\/mvc\/dao\/IMemberDao.java"},{"path":"\/jdbcTest\/src\/kr\/or\/ddit\/basic\/singlton","parentWorkspace":"D:\/A_TeachingMaterial\/3.HighJava","name":"MySingleton.java","lastModified":1611899001551,"locationURI":"file:\/D:\/A_TeachingMaterial\/3.HighJava\/jdbcTest\/src\/kr\/or\/ddit\/basic\/singlton\/MySingleton.java"}]}